Metadata-Version: 1.1
Name: shroud
Version: 0.1.0
Summary: Easy encryption/decryption for deployed secrets.
Home-page: http://github.com/mmedal/shroud/
Author: Matthew Medal
Author-email: matt.medal@gmail.com
License: MIT
Platform: UNKNOWN
Classifier: Intended Audience :: Developers
Classifier: License :: OSI Approved :: MIT License
Classifier: Operating System :: OS Independent
Classifier: Programming Language :: Python
Classifier: Programming Language :: Python :: 3
